pyqueen/__init__.py
pyqueen/analysis/__init__.py
pyqueen/analysis/model.py
pyqueen/chart/__init__.py
pyqueen/chart/plot.py
pyqueen/io/__init__.py
pyqueen/io/data_source.py
pyqueen/io/ds_plugin.py
pyqueen/io/excel.py
pyqueen/io/ftp.py
pyqueen/io/image.py
pyqueen/io/kvdb.py
pyqueen/io/sqldb.py
pyqueen/io/web.py
pyqueen/remote/__init__.py
pyqueen/remote/linux.py
pyqueen/service/__init__.py
pyqueen/service/finereport.py
pyqueen/service/pydingtalk.py
pyqueen/service/pyemail.py
pyqueen/service/pywechat.py
pyqueen/service/showdoc.py
pyqueen/utility/__init__.py
pyqueen/utility/command.py
pyqueen/utility/time_kit.py
pyqueen/utility/utils.py
pyqueen-1.2.0.dist-info/licenses/LICENSE
pyqueen-1.2.0.dist-info/METADATA
pyqueen-1.2.0.dist-info/WHEEL
pyqueen-1.2.0.dist-info/entry_points.txt
pyqueen-1.2.0.dist-info/top_level.txt
pyqueen-1.2.0.dist-info/RECORD
