Metadata-Version: 2.4
Name: pyqueen
Version: 1.2.0
Summary: Rule your Data
Home-page: https://github.com/ts7ming/pyqueen.git
Author: ts7ming
Author-email: qiming.ma@outlook.com
Classifier: Programming Language :: Python :: 3
Classifier: License :: OSI Approved :: MIT License
Classifier: Operating System :: OS Independent
Requires-Python: >=3.4
License-File: LICENSE
Requires-Dist: pandas>=2.0.0
Requires-Dist: SQLAlchemy>=2.0.0
Requires-Dist: xlrd==1.2.0
Requires-Dist: XlsxWriter
Dynamic: author
Dynamic: author-email
Dynamic: classifier
Dynamic: description
Dynamic: description-content-type
Dynamic: home-page
Dynamic: license-file
Dynamic: requires-dist
Dynamic: requires-python
Dynamic: summary
